{
  "records": [
    {
      "company": "Brown & Brown",
      "symbol": "BRO",
      "date": "2026-01-26",
      "bmo_amc": "TIME-AFTER-HOURS",
      "nasdaq_time_label": "time-after-hours",
      "yahoo_time_label": null,
      "source": "aggregator"
    },
    {
      "company": "W. R. Berkley Corp",
      "symbol": "WRB",
      "date": "2026-01-26",
      "bmo_amc": "TIME-AFTER-HOURS",
      "nasdaq_time_label": "time-after-hours",
      "yahoo_time_label": null,
      "source": "aggregator"
    },
    {
      "company": "Invesco",
      "symbol": "IVZ",
      "date": "2026-01-27",
      "bmo_amc": "TIME-PRE-MARKET",
      "nasdaq_time_label": "time-pre-market",
      "yahoo_time_label": null,
      "source": "aggregator"
    },
    {
      "company": "Synchrony Financial",
      "symbol": "SYF",
      "date": "2026-01-27",
      "bmo_amc": "8:00 AM ET",
      "nasdaq_time_label": "time-pre-market",
      "yahoo_time_label": null,
      "ir_time_label": "8:00 AM ET",
      "ir_source_url": "https://investors.synchrony.com/",
      "source": "investor_relations"
    },
    {
      "company": "MSCI Inc",
      "symbol": "MSCI",
      "date": "2026-01-28",
      "bmo_amc": "TIME-PRE-MARKET",
      "nasdaq_time_label": "time-pre-market",
      "yahoo_time_label": null,
      "source": "aggregator"
    },
    {
      "company": "Raymond James",
      "symbol": "RJF",
      "date": "2026-01-28",
      "bmo_amc": "TIME-AFTER-HOURS",
      "nasdaq_time_label": "time-after-hours",
      "yahoo_time_label": null,
      "source": "aggregator"
    },
    {
      "company": "Arthur J. Gallagher",
      "symbol": "AJG",
      "date": "2026-01-29",
      "bmo_amc": "TBD",
      "nasdaq_time_label": "time-not-supplied",
      "yahoo_time_label": null,
      "source": "aggregator"
    },
    {
      "company": "Blackstone",
      "symbol": "BX",
      "date": "2026-01-29",
      "bmo_amc": "TIME-PRE-MARKET",
      "nasdaq_time_label": "time-pre-market",
      "yahoo_time_label": null,
      "source": "aggregator"
    },
    {
      "company": "Hartford Financial Services",
      "symbol": "HIG",
      "date": "2026-01-29",
      "bmo_amc": "TIME-AFTER-HOURS",
      "nasdaq_time_label": "time-after-hours",
      "yahoo_time_label": null,
      "source": "aggregator"
    },
    {
      "company": "Lazard",
      "symbol": "LAZ",
      "date": "2026-01-29",
      "bmo_amc": "TBD",
      "nasdaq_time_label": "time-not-supplied",
      "yahoo_time_label": null,
      "source": "aggregator"
    },
    {
      "company": "Marsh McLennan",
      "symbol": "MMC",
      "date": "2026-01-29",
      "bmo_amc": "TIME-PRE-MARKET",
      "nasdaq_time_label": "time-pre-market",
      "yahoo_time_label": null,
      "source": "aggregator"
    },
    {
      "company": "Mastercard",
      "symbol": "MA",
      "date": "2026-01-29",
      "bmo_amc": "TBD",
      "nasdaq_time_label": "time-not-supplied",
      "yahoo_time_label": null,
      "source": "aggregator"
    },
    {
      "company": "Nasdaq",
      "symbol": "NDAQ",
      "date": "2026-01-29",
      "bmo_amc": "TIME-PRE-MARKET",
      "nasdaq_time_label": "time-pre-market",
      "yahoo_time_label": null,
      "source": "aggregator"
    },
    {
      "company": "Visa",
      "symbol": "V",
      "date": "2026-01-29",
      "bmo_amc": "TBD",
      "nasdaq_time_label": "time-not-supplied",
      "yahoo_time_label": null,
      "source": "aggregator"
    },
    {
      "company": "American Express",
      "symbol": "AXP",
      "date": "2026-01-30",
      "bmo_amc": "TIME-PRE-MARKET",
      "nasdaq_time_label": "time-pre-market",
      "yahoo_time_label": null,
      "source": "aggregator"
    },
    {
      "company": "Aon",
      "symbol": "AON",
      "date": "2026-01-30",
      "bmo_amc": "7:30AM",
      "nasdaq_time_label": "time-not-supplied",
      "yahoo_time_label": null,
      "ir_time_label": "7:30am",
      "ir_source_url": "https://ir.aon.com/",
      "source": "investor_relations"
    },
    {
      "company": "Franklin Templeton",
      "symbol": "BEN",
      "date": "2026-01-30",
      "bmo_amc": "TIME-PRE-MARKET",
      "nasdaq_time_label": "time-pre-market",
      "yahoo_time_label": null,
      "source": "aggregator"
    }
  ],
  "count": 17,
  "missingPublic": [
    "CDPQ",
    "CPPIB"
  ],
  "tickerCount": 85,
  "generatedAt": "2026-01-10T15:46:36Z",
  "irCompanies": [
    "Aon",
    "Synchrony Financial"
  ],
  "fallbackCompanies": [
    "American Express",
    "Arthur J. Gallagher",
    "Blackstone",
    "Brown & Brown",
    "Franklin Templeton",
    "Hartford Financial Services",
    "Invesco",
    "Lazard",
    "MSCI Inc",
    "Marsh McLennan",
    "Mastercard",
    "Nasdaq",
    "Raymond James",
    "Visa",
    "W. R. Berkley Corp"
  ],
  "week": {
    "id": "2026-01-26",
    "start_date": "2026-01-26",
    "end_date": "2026-01-30",
    "label": "Week of Jan 26 to Jan 30"
  },
  "sector": "Finance",
  "sectorSlug": "finance",
  "downloadPath": "downloads/2026-01-26/earnings_finance_2026-01-26.csv"
}